cli.py
static_deployer/__init__.py
static_deployer/common/__init__.py
static_deployer/common/configuration.py
static_deployer/common/log.py
static_deployer/common/types.py
static_deployer/common/utils.py
static_deployer/providers/__init__.py
static_deployer/providers/cdn/__init__.py
static_deployer/providers/cdn/cloudfront.py
static_deployer/providers/storage/__init__.py
static_deployer/providers/storage/s3bucket.py
static_deployer-0.1.5.dist-info/LICENSE
static_deployer-0.1.5.dist-info/METADATA
static_deployer-0.1.5.dist-info/WHEEL
static_deployer-0.1.5.dist-info/entry_points.txt
static_deployer-0.1.5.dist-info/top_level.txt
static_deployer-0.1.5.dist-info/RECORD
